adaptive_shots/__init__.py
adaptive_shots/config.py
adaptive_shots/database/__init__.py
adaptive_shots/database/adaptive_shot_db.py
adaptive_shots/database/base.py
adaptive_shots/models/__init__.py
adaptive_shots/models/schemas.py
adaptive_shots/services/__init__.py
adaptive_shots/services/embedding_service.py
tests/__init__.py
tests/test_shots.py
adaptive_shots-0.1.0.dist-info/LICENSE
adaptive_shots-0.1.0.dist-info/METADATA
adaptive_shots-0.1.0.dist-info/WHEEL
adaptive_shots-0.1.0.dist-info/top_level.txt
adaptive_shots-0.1.0.dist-info/RECORD
