Metadata-Version: 2.1
Name: adaptive-shots
Version: 0.1.0
Summary: A Python package for a simple adaptive few-shots prompting engine using a contextual combinatorial bandits algorithm.
Home-page: https://github.com/gokhanmeteerturk/adaptive-shots
Author: Gökhan Mete Ertürk
Author-email: 8rlvjfxsh@mozmail.com
Classifier: Programming Language :: Python :: 3
Classifier: License :: OSI Approved :: GNU General Public License v3 (GPLv3)
Classifier: Operating System :: OS Independent
Requires-Python: >=3.9
License-File: LICENSE
